autodiff26/__init__.py
autodiff26/forward_mode/__init__.py
autodiff26/forward_mode/ad_calculator.py
autodiff26/forward_mode/functions.py
autodiff26/reverse_mode/__init__.py
autodiff26/reverse_mode/reverse_calculator.py
autodiff26/reverse_mode/reverse_functions.py
autodiff26-0.0.2.dist-info/LICENSE
autodiff26-0.0.2.dist-info/METADATA
autodiff26-0.0.2.dist-info/WHEEL
autodiff26-0.0.2.dist-info/top_level.txt
autodiff26-0.0.2.dist-info/RECORD
