Metadata-Version: 2.1
Name: autodiff26
Version: 0.0.2
Summary: An Automatic Differentiation Package
Author-email: Wesley Osogo <Wesleyosogo@college.harvard.edu>, Yeabsira Tofik Mohammed <yeabsiramohammed@college.harvard.edu>, Aditya David Wirawan <adityawirawan@college.harvard.edu>, Roy Allan Ochieng Onyando <onyandoonyando@college.harvard.edu>, Toby Ruiduo Ma <tobyma@college.harvard.edu>
Project-URL: Homepage, https://code.harvard.edu/pages/CS107/team26/
Classifier: Programming Language :: Python :: 3
Classifier: License :: OSI Approved :: MIT License
Classifier: Operating System :: OS Independent
Requires-Python: >=3.7
License-File: LICENSE
Requires-Dist: numpy (>=1.22.0)
